omopmodel/OMOP_5_3_dataclasses.py
omopmodel/OMOP_5_3_declarative.py
omopmodel/OMOP_5_3_sqlmodels.py
omopmodel/OMOP_5_3_tables.py
omopmodel/OMOP_5_4_dataclasses.py
omopmodel/OMOP_5_4_declarative.py
omopmodel/OMOP_5_4_sqlmodels.py
omopmodel/OMOP_5_4_tables.py
omopmodel/__init__.py
omopmodel/vocabularies_loader.py
dzdomop-0.4.0.dist-info/METADATA
dzdomop-0.4.0.dist-info/WHEEL
dzdomop-0.4.0.dist-info/top_level.txt
dzdomop-0.4.0.dist-info/RECORD
