Metadata-Version: 2.2
Name: dzdomop
Version: 0.4.0
Summary: A Python ORM/data classes representation of the OMOP Common Data Model in different flavors powered by sqlacodegen
Author-email: Tim Bleimehl <bleimehl@helmholtz-munich.de>
License: MIT
Project-URL: Source, https://github.com/DZD-eV-Diabetes-Research/dzd-omop-cdm-python-models
Project-URL: Issues, https://github.com/DZD-eV-Diabetes-Research/dzd-omop-cdm-python-models/issues
Keywords: DZD,OMOP
Classifier: Programming Language :: Python :: 3
Classifier: Programming Language :: Python :: 3.10
Classifier: Programming Language :: Python :: 3.11
Classifier: Programming Language :: Python :: 3.12
Requires-Python: >=3.10
Requires-Dist: sqlmodel
Requires-Dist: sqlalchemy
Requires-Dist: tqdm
Requires-Dist: pg8000
Provides-Extra: test
Requires-Dist: pytest; extra == "test"
Requires-Dist: deepdiff; extra == "test"
Provides-Extra: docs
Requires-Dist: mkdocs; extra == "docs"
Requires-Dist: mkdocstrings[python]; extra == "docs"
Requires-Dist: mkdocs-autorefs; extra == "docs"
Requires-Dist: mkdocs-material; extra == "docs"
